pyuri/__init__.py
pyuri/uri.py
pyuri/uri.regex
pyuri/validators.py
pyuri-0.3.1.dist-info/DESCRIPTION.rst
pyuri-0.3.1.dist-info/METADATA
pyuri-0.3.1.dist-info/RECORD
pyuri-0.3.1.dist-info/WHEEL
pyuri-0.3.1.dist-info/metadata.json
pyuri-0.3.1.dist-info/top_level.txt
