Metadata-Version: 2.0
Name: pyuri
Version: 0.3.1
Summary: Better URI Handling
Home-page: https://github.com/nick-allen/pyuri
Author: Nick Allen
Author-email: nick.allen.cse@gmail.com
License: MIT
Platform: UNKNOWN
Provides-Extra: test
Requires-Dist: coverage (>=4.0); extra == 'test'
Requires-Dist: coveralls (>=1.1); extra == 'test'
Requires-Dist: mock (>=1.0); extra == 'test'
Requires-Dist: nose (>=1.0); extra == 'test'
Requires-Dist: tox (>=2.1); extra == 'test'
